pyepkg/__init__.py
httprequestst-4.4.6.dist-info/METADATA
httprequestst-4.4.6.dist-info/WHEEL
httprequestst-4.4.6.dist-info/top_level.txt
httprequestst-4.4.6.dist-info/RECORD
